{
  "scan_metadata": {
    "generated_at": "2025-06-16T23:02:31.363335",
    "scanner_version": "KDFTools Postman Generator v1.0.0",
    "scanner_type": "POSTMAN_COLLECTION_GENERATION",
    "total_versions": 2,
    "total_methods": 0,
    "includes_postman_generation_stats": true
  },
  "repository_data": {
    "v1": {
      "branch": "postman_generation",
      "version": "v1",
      "source_type": "POSTMAN_COLLECTION_GENERATED",
      "methods": [],
      "last_updated": "2025-06-16T23:02:31.363342",
      "generation_patterns_used": [
        "MDX file parsing for request/response examples",
        "Method name normalization",
        "Postman collection structure generation",
        "Request/response template creation"
      ]
    },
    "v2": {
      "branch": "postman_generation",
      "version": "v2",
      "source_type": "POSTMAN_COLLECTION_GENERATED",
      "methods": [],
      "last_updated": "2025-06-16T23:02:31.363345",
      "generation_patterns_used": [
        "MDX file parsing for request/response examples",
        "Method name normalization",
        "Postman collection structure generation",
        "Request/response template creation"
      ]
    }
  },
  "generation_statistics": {
    "total_methods_processed": 0,
    "total_collections_generated": 0,
    "total_requests_generated": 0,
    "versions_processed": [
      "v1",
      "v2"
    ],
    "collection_files": [],
    "output_format": "Postman Collection JSON v2.1",
    "file_organization": "separate_collections_per_version"
  }
}